slackbot_atlassian-0.1.dist-info/DESCRIPTION.rst
slackbot_atlassian-0.1.dist-info/METADATA
slackbot_atlassian-0.1.dist-info/RECORD
slackbot_atlassian-0.1.dist-info/WHEEL
slackbot_atlassian-0.1.dist-info/metadata.json
slackbot_atlassian-0.1.dist-info/top_level.txt
slackbotatlassian/__init__.py
slackbotatlassian/jira.py
